MANIFEST.in
README.md
setup.cfg
setup.py
sklearn_hierarchical_classification/__init__.py
sklearn_hierarchical_classification/array.py
sklearn_hierarchical_classification/classifier.py
sklearn_hierarchical_classification/constants.py
sklearn_hierarchical_classification/decorators.py
sklearn_hierarchical_classification/dummy.py
sklearn_hierarchical_classification/graph.py
sklearn_hierarchical_classification/metrics.py
sklearn_hierarchical_classification/validation.py
sklearn_hierarchical_classification.egg-info/PKG-INFO
sklearn_hierarchical_classification.egg-info/SOURCES.txt
sklearn_hierarchical_classification.egg-info/dependency_links.txt
sklearn_hierarchical_classification.egg-info/not-zip-safe
sklearn_hierarchical_classification.egg-info/requires.txt
sklearn_hierarchical_classification.egg-info/top_level.txt