Metadata-Version: 2.1
Name: sklearn-hierarchical-classification
Version: 1.3.2
Summary: Hierarchical classification interface extensions for scikit-learn
Home-page: https://github.com/globality-corp/sklearn-hierarchical-classification
Author: Globality Engineering
Author-email: engineering@globality.com
License: UNKNOWN
Platform: UNKNOWN
Provides-Extra: test
